box/__init__.py
box/frame.py
BoxFramework-0.2.1.dist-info/LICENSE
BoxFramework-0.2.1.dist-info/METADATA
BoxFramework-0.2.1.dist-info/WHEEL
BoxFramework-0.2.1.dist-info/top_level.txt
BoxFramework-0.2.1.dist-info/RECORD
