Metadata-Version: 2.1
Name: BoxFramework
Version: 0.2.1
Summary: A framework desgined to provide useful functions
Author-email: Boxei <boxeigit@gmail.com>
Project-URL: Homepage, https://github.com/Boxei/Box
Project-URL: Bug Tracker, https://github.com/Boxei/Box/issues
Classifier: Programming Language :: Python :: 3
Classifier: License :: OSI Approved :: MIT License
Classifier: Operating System :: OS Independent
Requires-Python: >=3.7
License-File: LICENSE
